stable_solvers/__init__.py
stable_solvers/autograd.py
stable_solvers/distributed.py
stable_solvers/eigen.py
stable_solvers/jacobians.py
stable_solvers/loss_functions.py
stable_solvers/operators.py
stable_solvers/solvers.py
stable_solvers/utils.py
stable_solvers-0.1.dist-info/METADATA
stable_solvers-0.1.dist-info/WHEEL
stable_solvers-0.1.dist-info/top_level.txt
stable_solvers-0.1.dist-info/RECORD
