Metadata-Version: 2.1
Name: stable-solvers
Version: 0.1
Summary: Library of solvers to train neural networks without entering the edge of stability
Author-email: Mark Lowell <MarkLowell@theorem-engine.org>
Requires-Dist: torch >=2.1
